setup.cfg
setup.py
sasha/__init__.py
sasha/interfaces.py
sasha/master.py
sasha.egg-info/PKG-INFO
sasha.egg-info/SOURCES.txt
sasha.egg-info/dependency_links.txt
sasha.egg-info/entry_points.txt
sasha.egg-info/requires.txt
sasha.egg-info/top_level.txt